README.txt
setup.py
gizmo/__init__.py
gizmo/client.py
gizmo/connection.py
gizmo/exceptions.py
gizmo/handlers.py
gizmo/response.py
gizmo/tasks.py
gizmo.egg-info/PKG-INFO
gizmo.egg-info/SOURCES.txt
gizmo.egg-info/dependency_links.txt
gizmo.egg-info/requires.txt
gizmo.egg-info/top_level.txt
gizmo/tests/__init__.py
gizmo/tests/tests.py