Metadata-Version: 1.1
Name: gizmo
Version: 0.1.12
Summary: Async Python 3 driver for TP3 Gremlin Server
Home-page: UNKNOWN
Author: davebshow
Author-email: davebshow@gmail.com
License: MIT
Platform: UNKNOWN
Classifier: Development Status :: 3 - Alpha
Classifier: Intended Audience :: Developers
Classifier: License :: OSI Approved :: MIT License
Classifier: Operating System :: OS Independent
Classifier: Programming Language :: Python
Classifier: Programming Language :: Python :: 3.4
Classifier: Programming Language :: Python :: 3 :: Only
